kick_sdk/example.py
kick_sdk/kick_sdk.py
kick_sdk/simple_moderation_bot.py
kick_sdk/data/authenticated_user.py
kick_sdk/data/message_entry.py
kick_sdk/util/logger.py
kick_sdk-1.0.1.dist-info/LICENSE
kick_sdk-1.0.1.dist-info/METADATA
kick_sdk-1.0.1.dist-info/WHEEL
kick_sdk-1.0.1.dist-info/top_level.txt
kick_sdk-1.0.1.dist-info/RECORD
